pylotiger.py
pylotiger-1.0.dist-info/LICENSE
pylotiger-1.0.dist-info/METADATA
pylotiger-1.0.dist-info/WHEEL
pylotiger-1.0.dist-info/top_level.txt
pylotiger-1.0.dist-info/RECORD
