Metadata-Version: 2.1
Name: pylotiger
Version: 1.0
Summary: Python Package for Original and Corrected TIGER Rate Calculation
Home-page: https://github.com/pylogeny/tiger
Author: Johann-Mattis List
Author-email: mattis_list@eva.mpg.de
License: MIT
Keywords: phylogeny
Platform: any
Classifier: Programming Language :: Python
Classifier: Programming Language :: Python :: 3
Classifier: Programming Language :: Python :: 3.6
Classifier: Programming Language :: Python :: 3.7
Classifier: Programming Language :: Python :: 3.8
Classifier: Programming Language :: Python :: 3.9
Requires-Python: >=3.6
License-File: LICENSE
Provides-Extra: dev
Requires-Dist: wheel ; extra == 'dev'
Requires-Dist: twine ; extra == 'dev'
Provides-Extra: test
Requires-Dist: pytest (>=4.3) ; extra == 'test'
Requires-Dist: pytest-cov ; extra == 'test'
Requires-Dist: coverage (>=4.2) ; extra == 'test'
